{
  "file_name": "studio_pixel_bloom.piuser.json",
  "profile_version": 1,
  "user_identity": {
    "username": "studio_pixel_bloom",
    "account_identifier": "studiopixelbloomcreations@gmail.com",
    "system_user_id": "vis_mnj6ezdi_rz12vlix",
    "creation_timestamp": "2026-04-03T17:27:17.910Z"
  },
  "facial_signature": {
    "scan_mode": "infrared_assisted",
    "frame_count": 1,
    "landmark_vectors": [
      [
        {
          "name": "p0",
          "x": 0.32670677432906814,
          "y": 0.43145696963700986
        },
        {
          "name": "p1",
          "x": 0.3276526450063102,
          "y": 0.49815567487643825
        },
        {
          "name": "p2",
          "x": 0.3322093852329999,
          "y": 0.5620507852070862
        },
        {
          "name": "p3",
          "x": 0.33692037442233413,
          "y": 0.6162619613938861
        },
        {
          "name": "p4",
          "x": 0.34585881687235087,
          "y": 0.6780123917592896
        },
        {
          "name": "p5",
          "x": 0.3632409821730107,
          "y": 0.7271376618908512
        },
        {
          "name": "p6",
          "x": 0.3858460206538439,
          "y": 0.7635717617968718
        },
        {
          "name": "p7",
          "x": 0.41637026565149426,
          "y": 0.7988339229590363
        },
        {
          "name": "p8",
          "x": 0.45812222734093666,
          "y": 0.821828855574131
        },
        {
          "name": "p9",
          "x": 0.4985509654507041,
          "y": 0.8047217075195577
        },
        {
          "name": "p10",
          "x": 0.5223842365667224,
          "y": 0.7793316298888789
        },
        {
          "name": "p11",
          "x": 0.5418221885338426,
          "y": 0.7546595764656862
        },
        {
          "name": "p12",
          "x": 0.5593591183423996,
          "y": 0.7096820967892806
        },
        {
          "name": "p13",
          "x": 0.5730380360037088,
          "y": 0.653197270217869
        },
        {
          "name": "p14",
          "x": 0.58114152867347,
          "y": 0.5998593497607443
        },
        {
          "name": "p15",
          "x": 0.5891027823090553,
          "y": 0.5424430294997162
        },
        {
          "name": "p16",
          "x": 0.5930864568799734,
          "y": 0.4798406206485298
        },
        {
          "name": "p17",
          "x": 0.36319363908842206,
          "y": 0.3816801470807857
        },
        {
          "name": "p18",
          "x": 0.3811357815284282,
          "y": 0.35894284163498213
        },
        {
          "name": "p19",
          "x": 0.4027273510582745,
          "y": 0.35689723764856657
        },
        {
          "name": "p20",
          "x": 0.42209202237427235,
          "y": 0.3660623189682762
        },
        {
          "name": "p21",
          "x": 0.43859076872467995,
          "y": 0.37980086631659005
        },
        {
          "name": "p22",
          "x": 0.5104381842538714,
          "y": 0.3919345588112871
        },
        {
          "name": "p23",
          "x": 0.5264256838709116,
          "y": 0.3824571237175001
        },
        {
          "name": "p24",
          "x": 0.5448874682188034,
          "y": 0.37868329694287645
        },
        {
          "name": "p25",
          "x": 0.5644992608577013,
          "y": 0.3852243155447973
        },
        {
          "name": "p26",
          "x": 0.5763365123420954,
          "y": 0.4105713768965668
        },
        {
          "name": "p27",
          "x": 0.4717836184427142,
          "y": 0.4679665070441034
        },
        {
          "name": "p28",
          "x": 0.4713502358645201,
          "y": 0.5128717207660277
        },
        {
          "name": "p29",
          "x": 0.4712038328871131,
          "y": 0.5543979478379091
        },
        {
          "name": "p30",
          "x": 0.46958752628415823,
          "y": 0.5908254258334636
        },
        {
          "name": "p31",
          "x": 0.4461887697689235,
          "y": 0.614646459205283
        },
        {
          "name": "p32",
          "x": 0.45568266324698925,
          "y": 0.6217904201812214
        },
        {
          "name": "p33",
          "x": 0.4671002272516489,
          "y": 0.6265467990603711
        },
        {
          "name": "p34",
          "x": 0.47885461151599884,
          "y": 0.6226422418322828
        },
        {
          "name": "p35",
          "x": 0.48757452610880136,
          "y": 0.6206223848793242
        },
        {
          "name": "p36",
          "x": 0.3871843800880015,
          "y": 0.4419013256414069
        },
        {
          "name": "p37",
          "x": 0.40082357404753566,
          "y": 0.4353178919603427
        },
        {
          "name": "p38",
          "x": 0.4183369926176965,
          "y": 0.4387353553954098
        },
        {
          "name": "p39",
          "x": 0.43283296935260296,
          "y": 0.45762395420008234
        },
        {
          "name": "p40",
          "x": 0.4198071495629847,
          "y": 0.4661615659379297
        },
        {
          "name": "p41",
          "x": 0.40040263580158353,
          "y": 0.46022575510044894
        },
        {
          "name": "p42",
          "x": 0.5050129778683186,
          "y": 0.4678171829630931
        },
        {
          "name": "p43",
          "x": 0.5214935010299087,
          "y": 0.45317423947983315
        },
        {
          "name": "p44",
          "x": 0.5392456892877817,
          "y": 0.4545171629223559
        },
        {
          "name": "p45",
          "x": 0.5485961958765984,
          "y": 0.46790142063465384
        },
        {
          "name": "p46",
          "x": 0.5367994913831353,
          "y": 0.4812864799466398
        },
        {
          "name": "p47",
          "x": 0.5188040845096111,
          "y": 0.4770983306898011
        },
        {
          "name": "p48",
          "x": 0.4203269141726196,
          "y": 0.6959010646575027
        },
        {
          "name": "p49",
          "x": 0.4376386348158121,
          "y": 0.6829522672626708
        },
        {
          "name": "p50",
          "x": 0.456537839025259,
          "y": 0.6745965315235986
        },
        {
          "name": "p51",
          "x": 0.46636664494872093,
          "y": 0.678382661110825
        },
        {
          "name": "p52",
          "x": 0.47575317043811083,
          "y": 0.6746406543585989
        },
        {
          "name": "p53",
          "x": 0.4948021024465561,
          "y": 0.6911140158772469
        },
        {
          "name": "p54",
          "x": 0.5091269062831998,
          "y": 0.7043579762180646
        },
        {
          "name": "p55",
          "x": 0.49378686025738716,
          "y": 0.7233440390891499
        },
        {
          "name": "p56",
          "x": 0.48022144567221403,
          "y": 0.7354866363108158
        },
        {
          "name": "p57",
          "x": 0.4646985661238432,
          "y": 0.7379713165263335
        },
        {
          "name": "p58",
          "x": 0.45036414405331016,
          "y": 0.7329336807131768
        },
        {
          "name": "p59",
          "x": 0.43507259292528033,
          "y": 0.7204287604325348
        },
        {
          "name": "p60",
          "x": 0.42273968178778887,
          "y": 0.6966000944375992
        },
        {
          "name": "p61",
          "x": 0.45118676824495196,
          "y": 0.694465155651172
        },
        {
          "name": "p62",
          "x": 0.4653936754912138,
          "y": 0.6954212201138338
        },
        {
          "name": "p63",
          "x": 0.4785422049462795,
          "y": 0.6977936415208711
        },
        {
          "name": "p64",
          "x": 0.5053754625841975,
          "y": 0.703503331542015
        },
        {
          "name": "p65",
          "x": 0.47920270450413227,
          "y": 0.7078150665594471
        },
        {
          "name": "p66",
          "x": 0.46603675931692123,
          "y": 0.7088428219159444
        },
        {
          "name": "p67",
          "x": 0.4524068273603916,
          "y": 0.7063416914807426
        },
        {
          "name": "left_eye",
          "x": 0.4098979502450675,
          "y": 0.4499943080392701
        },
        {
          "name": "right_eye",
          "x": 0.5283253233258922,
          "y": 0.46696580277272953
        },
        {
          "name": "nose",
          "x": 0.47784312162548304,
          "y": 0.623270475257326
        },
        {
          "name": "mouth_left",
          "x": 0.4203269141726196,
          "y": 0.6959010646575027
        },
        {
          "name": "mouth_right",
          "x": 0.5091269062831998,
          "y": 0.7043579762180646
        }
      ]
    ],
    "feature_embedding": [
      -0.026858745142817497,
      0.1094161719083786,
      0.10047416388988495,
      -0.04151342809200287,
      -0.04902927204966545,
      -0.012103199027478695,
      0.012918950989842415,
      -0.049674734473228455,
      0.183319091796875,
      -0.10069265216588974,
      0.24950957298278809,
      -0.04745987430214882,
      -0.16286173462867737,
      -0.12254653871059418,
      -0.036202773451805115,
      0.09676432609558105,
      -0.09096506237983704,
      -0.10045184195041656,
      -0.11159736663103104,
      -0.12518517673015594,
      0.012520996853709221,
      0.024701427668333054,
      0.012982002459466457,
      -0.02614530548453331,
      -0.12624415755271912,
      -0.340829461812973,
      -0.0357402078807354,
      -0.13209979236125946,
      0.07754414528608322,
      -0.15774589776992798,
      0.02660648711025715,
      0.10845448076725006,
      -0.2331186980009079,
      -0.04090401902794838,
      -0.075363889336586,
      0.04671608656644821,
      0.011819474399089813,
      -0.001261983416043222,
      0.1591249704360962,
      0.0326925553381443,
      -0.18137143552303314,
      -0.015001075342297554,
      -0.02996632270514965,
      0.24312658607959747,
      0.18568196892738342,
      -0.008930771611630917,
      -0.005863577127456665,
      -0.06131570041179657,
      0.015762433409690857,
      -0.16380973160266876,
      0.11371763795614243,
      0.10227076709270477,
      0.07655921578407288,
      0.0479242317378521,
      0.0663256049156189,
      -0.13355980813503265,
      -0.013974854722619057,
      0.05602889508008957,
      -0.2203601449728012,
      -0.008046524599194527,
      0.050411880016326904,
      -0.042878761887550354,
      -0.11712879687547684,
      -0.038852836936712265,
      0.2752227187156677,
      0.13487371802330017,
      -0.08841326087713242,
      -0.13332116603851318,
      0.2264167219400406,
      -0.1479962170124054,
      -0.010016991756856441,
      0.08805955201387405,
      -0.06435393542051315,
      -0.06851520389318466,
      -0.3048771619796753,
      0.10824482142925262,
      0.4002099633216858,
      0.11655513942241669,
      -0.20402075350284576,
      0.03049473650753498,
      -0.1534789353609085,
      -0.026471581310033798,
      0.06178053468465805,
      0.06194351613521576,
      -0.11983954906463623,
      0.07665475457906723,
      -0.007810684386640787,
      0.031163472682237625,
      0.07923293113708496,
      0.06958449631929398,
      -0.11270512640476227,
      0.1838023066520691,
      -0.046265266835689545,
      -0.022907927632331848,
      0.04758550226688385,
      -0.05304834246635437,
      -0.07240930944681168,
      -0.036477889865636826,
      -0.13195089995861053,
      -0.07560758292675018,
      0.052874498069286346,
      -0.10144662111997604,
      -0.05115894228219986,
      0.1571553498506546,
      -0.20663440227508545,
      0.16859987378120422,
      0.0062685757875442505,
      -0.03729298338294029,
      0.048517122864723206,
      0.03357860445976257,
      -0.04957381263375282,
      -0.038012344390153885,
      0.17803554236888885,
      -0.2922457158565521,
      0.17194285988807678,
      0.10148291289806366,
      0.06058766320347786,
      0.15513549745082855,
      0.11060553789138794,
      0.0944652333855629,
      -0.00736944330856204,
      -0.05362071841955185,
      -0.192814901471138,
      -0.014516246505081654,
      0.05993780493736267,
      -0.07309714704751968,
      0.07844424992799759,
      0.057438865303993225
    ],
    "feature_vector": [
      -0.026858745142817497,
      0.1094161719083786,
      0.10047416388988495,
      -0.04151342809200287,
      -0.04902927204966545,
      -0.012103199027478695,
      0.012918950989842415,
      -0.049674734473228455,
      0.183319091796875,
      -0.10069265216588974,
      0.24950957298278809,
      -0.04745987430214882,
      -0.16286173462867737,
      -0.12254653871059418,
      -0.036202773451805115,
      0.09676432609558105,
      -0.09096506237983704,
      -0.10045184195041656,
      -0.11159736663103104,
      -0.12518517673015594,
      0.012520996853709221,
      0.024701427668333054,
      0.012982002459466457,
      -0.02614530548453331,
      -0.12624415755271912,
      -0.340829461812973,
      -0.0357402078807354,
      -0.13209979236125946,
      0.07754414528608322,
      -0.15774589776992798,
      0.02660648711025715,
      0.10845448076725006,
      -0.2331186980009079,
      -0.04090401902794838,
      -0.075363889336586,
      0.04671608656644821,
      0.011819474399089813,
      -0.001261983416043222,
      0.1591249704360962,
      0.0326925553381443,
      -0.18137143552303314,
      -0.015001075342297554,
      -0.02996632270514965,
      0.24312658607959747,
      0.18568196892738342,
      -0.008930771611630917,
      -0.005863577127456665,
      -0.06131570041179657,
      0.015762433409690857,
      -0.16380973160266876,
      0.11371763795614243,
      0.10227076709270477,
      0.07655921578407288,
      0.0479242317378521,
      0.0663256049156189,
      -0.13355980813503265,
      -0.013974854722619057,
      0.05602889508008957,
      -0.2203601449728012,
      -0.008046524599194527,
      0.050411880016326904,
      -0.042878761887550354,
      -0.11712879687547684,
      -0.038852836936712265,
      0.2752227187156677,
      0.13487371802330017,
      -0.08841326087713242,
      -0.13332116603851318,
      0.2264167219400406,
      -0.1479962170124054,
      -0.010016991756856441,
      0.08805955201387405,
      -0.06435393542051315,
      -0.06851520389318466,
      -0.3048771619796753,
      0.10824482142925262,
      0.4002099633216858,
      0.11655513942241669,
      -0.20402075350284576,
      0.03049473650753498,
      -0.1534789353609085,
      -0.026471581310033798,
      0.06178053468465805,
      0.06194351613521576,
      -0.11983954906463623,
      0.07665475457906723,
      -0.007810684386640787,
      0.031163472682237625,
      0.07923293113708496,
      0.06958449631929398,
      -0.11270512640476227,
      0.1838023066520691,
      -0.046265266835689545,
      -0.022907927632331848,
      0.04758550226688385,
      -0.05304834246635437,
      -0.07240930944681168,
      -0.036477889865636826,
      -0.13195089995861053,
      -0.07560758292675018,
      0.052874498069286346,
      -0.10144662111997604,
      -0.05115894228219986,
      0.1571553498506546,
      -0.20663440227508545,
      0.16859987378120422,
      0.0062685757875442505,
      -0.03729298338294029,
      0.048517122864723206,
      0.03357860445976257,
      -0.04957381263375282,
      -0.038012344390153885,
      0.17803554236888885,
      -0.2922457158565521,
      0.17194285988807678,
      0.10148291289806366,
      0.06058766320347786,
      0.15513549745082855,
      0.11060553789138794,
      0.0944652333855629,
      -0.00736944330856204,
      -0.05362071841955185,
      -0.192814901471138,
      -0.014516246505081654,
      0.05993780493736267,
      -0.07309714704751968,
      0.07844424992799759,
      0.057438865303993225
    ],
    "signature_model": "faceapi",
    "symmetry_metrics": {
      "embedding_dimensions": 128,
      "sample_count": 1
    },
    "geometry_map": {
      "geometry_snapshots": [
        {
          "box": {
            "x": 0.31930243968963623,
            "y": 0.24867664443122017,
            "width": 0.26623964309692383,
            "height": 0.5848589738210042
          },
          "pose_hint": "center",
          "emotion": "neutral",
          "captured_at": "2026-04-03T17:27:13.816Z"
        }
      ],
      "extraction": "face-api.js browser registration"
    },
    "created_at": "2026-04-03T17:27:17.910Z"
  },
  "personalization_profile": {
    "interests": [],
    "behavior_patterns": [],
    "conversation_habits": [],
    "preferred_interaction_style": "balanced",
    "frequently_discussed_topics": [],
    "tone_preferences": "adaptive"
  },
  "conversation_memory": {
    "history": [],
    "important_facts": {}
  },
  "learned_preferences": {},
  "ai_behavior_configuration": {
    "preferred_conversation_tone": "adaptive",
    "formality_level": "balanced",
    "response_length_preference": "balanced",
    "technical_explanation_depth": "adaptive",
    "humor_professional_balance": "balanced"
  },
  "session_state": {
    "paused": false,
    "assistant_state": "idle",
    "pending_messages": [],
    "pending_response": null,
    "last_active_timestamp": "2026-04-03T17:27:17.910Z"
  },
  "face_registration": {
    "provider": "face-api.js",
    "registered_frames": 1,
    "coverage": []
  }
}
